{"box_data": [{"position": {"minX": 462.25, "minY": 147.75, "maxX": 622.0, "maxY": 256.0}, "class_id": 1, "box_caption": "DRONE 0.017", "scores": {"class_score": 0.0172576904296875}, "domain": "pixel"}, {"position": {"minX": 447.0, "minY": 142.25, "maxX": 573.0, "maxY": 259.75}, "class_id": 1, "box_caption": "DRONE 0.017", "scores": {"class_score": 0.0170745849609375}, "domain": "pixel"}, {"position": {"minX": 398.25, "minY": 137.375, "maxX": 556.0, "maxY": 259.25}, "class_id": 1, "box_caption": "DRONE 0.016", "scores": {"class_score": 0.0157470703125}, "domain": "pixel"}, {"position": {"minX": 369.5, "minY": 542.0, "maxX": 622.5, "maxY": 669.0}, "class_id": 1, "box_caption": "DRONE 0.015", "scores": {"class_score": 0.0153656005859375}, "domain": "pixel"}, {"position": {"minX": 319.5, "minY": 391.75, "maxX": 522.5, "maxY": 594.0}, "class_id": 1, "box_caption": "DRONE 0.015", "scores": {"class_score": 0.01513671875}, "domain": "pixel"}, {"position": {"minX": -54.4375, "minY": 352.25, "maxX": 274.75, "maxY": 426.75}, "class_id": 1, "box_caption": "DRONE 0.015", "scores": {"class_score": 0.01512908935546875}, "domain": "pixel"}, {"position": {"minX": 546.5, "minY": 352.75, "maxX": 674.5, "maxY": 488.75}, "class_id": 0, "box_caption": "AIRPLANE 0.015", "scores": {"class_score": 0.0146484375}, "domain": "pixel"}, {"position": {"minX": 363.75, "minY": 127.25, "maxX": 519.5, "maxY": 255.25}, "class_id": 1, "box_caption": "DRONE 0.014", "scores": {"class_score": 0.0142822265625}, "domain": "pixel"}, {"position": {"minX": -43.6875, "minY": 341.75, "maxX": 266.25, "maxY": 363.25}, "class_id": 1, "box_caption": "DRONE 0.014", "scores": {"class_score": 0.01425933837890625}, "domain": "pixel"}, {"position": {"minX": -94.75, "minY": 559.5, "maxX": 183.75, "maxY": 659.5}, "class_id": 0, "box_caption": "AIRPLANE 0.014", "scores": {"class_score": 0.0142059326171875}, "domain": "pixel"}, {"position": {"minX": -364.0, "minY": -273.5, "maxX": 539.0, "maxY": 540.0}, "class_id": 1, "box_caption": "DRONE 0.014", "scores": {"class_score": 0.01393890380859375}, "domain": "pixel"}, {"position": {"minX": -297.0, "minY": 83.0, "maxX": 606.0, "maxY": 701.0}, "class_id": 1, "box_caption": "DRONE 0.014", "scores": {"class_score": 0.01387786865234375}, "domain": "pixel"}, {"position": {"minX": 534.0, "minY": 269.0, "maxX": 686.0, "maxY": 517.5}, "class_id": 0, "box_caption": "AIRPLANE 0.014", "scores": {"class_score": 0.0137481689453125}, "domain": "pixel"}, {"position": {"minX": 438.0, "minY": 329.0, "maxX": 724.0, "maxY": 409.5}, "class_id": 1, "box_caption": "DRONE 0.014", "scores": {"class_score": 0.01369476318359375}, "domain": "pixel"}, {"position": {"minX": 407.75, "minY": 494.75, "maxX": 570.0, "maxY": 654.0}, "class_id": 1, "box_caption": "DRONE 0.013", "scores": {"class_score": 0.01313018798828125}, "domain": "pixel"}, {"position": {"minX": 340.75, "minY": 129.25, "maxX": 478.25, "maxY": 241.5}, "class_id": 1, "box_caption": "DRONE 0.013", "scores": {"class_score": 0.013031005859375}, "domain": "pixel"}, {"position": {"minX": 617.5, "minY": 294.0, "maxX": 639.5, "maxY": 379.0}, "class_id": 1, "box_caption": "DRONE 0.013", "scores": {"class_score": 0.0128936767578125}, "domain": "pixel"}, {"position": {"minX": 475.25, "minY": 355.0, "maxX": 695.0, "maxY": 445.0}, "class_id": 1, "box_caption": "DRONE 0.012", "scores": {"class_score": 0.01209259033203125}, "domain": "pixel"}, {"position": {"minX": 464.0, "minY": 518.0, "maxX": 568.0, "maxY": 633.0}, "class_id": 1, "box_caption": "DRONE 0.012", "scores": {"class_score": 0.01206207275390625}, "domain": "pixel"}, {"position": {"minX": 408.5, "minY": 175.5, "maxX": 607.0, "maxY": 285.75}, "class_id": 1, "box_caption": "DRONE 0.012", "scores": {"class_score": 0.0120391845703125}, "domain": "pixel"}, {"position": {"minX": 385.75, "minY": 453.25, "maxX": 581.5, "maxY": 617.0}, "class_id": 1, "box_caption": "DRONE 0.012", "scores": {"class_score": 0.01194000244140625}, "domain": "pixel"}, {"position": {"minX": 438.5, "minY": 485.0, "maxX": 586.5, "maxY": 588.0}, "class_id": 1, "box_caption": "DRONE 0.012", "scores": {"class_score": 0.01194000244140625}, "domain": "pixel"}, {"position": {"minX": 623.0, "minY": 275.5, "maxX": 638.0, "maxY": 367.0}, "class_id": 1, "box_caption": "DRONE 0.012", "scores": {"class_score": 0.01190185546875}, "domain": "pixel"}, {"position": {"minX": 503.5, "minY": 534.5, "maxX": 612.5, "maxY": 632.5}, "class_id": 0, "box_caption": "AIRPLANE 0.012", "scores": {"class_score": 0.01189422607421875}, "domain": "pixel"}, {"position": {"minX": 508.0, "minY": 132.75, "maxX": 639.0, "maxY": 269.0}, "class_id": 1, "box_caption": "DRONE 0.012", "scores": {"class_score": 0.01175689697265625}, "domain": "pixel"}, {"position": {"minX": 457.0, "minY": 58.5625, "maxX": 579.0, "maxY": 204.0}, "class_id": 1, "box_caption": "DRONE 0.012", "scores": {"class_score": 0.01163482666015625}, "domain": "pixel"}, {"position": {"minX": 498.5, "minY": 303.75, "maxX": 612.5, "maxY": 346.25}, "class_id": 0, "box_caption": "AIRPLANE 0.012", "scores": {"class_score": 0.01158905029296875}, "domain": "pixel"}, {"position": {"minX": 498.5, "minY": 303.75, "maxX": 612.5, "maxY": 346.25}, "class_id": 1, "box_caption": "DRONE 0.011", "scores": {"class_score": 0.01140594482421875}, "domain": "pixel"}, {"position": {"minX": 492.75, "minY": 525.0, "maxX": 614.0, "maxY": 611.0}, "class_id": 1, "box_caption": "DRONE 0.011", "scores": {"class_score": 0.011077880859375}, "domain": "pixel"}, {"position": {"minX": 363.0, "minY": 65.8125, "maxX": 542.0, "maxY": 196.25}, "class_id": 1, "box_caption": "DRONE 0.011", "scores": {"class_score": 0.0110015869140625}, "domain": "pixel"}, {"position": {"minX": 453.5, "minY": 438.25, "maxX": 570.5, "maxY": 497.75}, "class_id": 1, "box_caption": "DRONE 0.011", "scores": {"class_score": 0.01093292236328125}, "domain": "pixel"}, {"position": {"minX": 336.5, "minY": 205.625, "maxX": 639.5, "maxY": 405.5}, "class_id": 1, "box_caption": "DRONE 0.011", "scores": {"class_score": 0.01079559326171875}, "domain": "pixel"}, {"position": {"minX": 638.5, "minY": 285.25, "maxX": 661.5, "maxY": 366.25}, "class_id": 1, "box_caption": "DRONE 0.011", "scores": {"class_score": 0.01070404052734375}, "domain": "pixel"}, {"position": {"minX": 176.0, "minY": -72.75, "maxX": 282.25, "maxY": 142.125}, "class_id": 1, "box_caption": "DRONE 0.011", "scores": {"class_score": 0.01067352294921875}, "domain": "pixel"}, {"position": {"minX": 388.75, "minY": 414.0, "maxX": 572.0, "maxY": 521.0}, "class_id": 1, "box_caption": "DRONE 0.011", "scores": {"class_score": 0.01067352294921875}, "domain": "pixel"}, {"position": {"minX": 346.5, "minY": 169.375, "maxX": 536.5, "maxY": 283.5}, "class_id": 1, "box_caption": "DRONE 0.011", "scores": {"class_score": 0.01055145263671875}, "domain": "pixel"}, {"position": {"minX": 493.5, "minY": 640.5, "maxX": 503.0, "maxY": 646.5}, "class_id": 0, "box_caption": "AIRPLANE 0.010", "scores": {"class_score": 0.010498046875}, "domain": "pixel"}, {"position": {"minX": 350.5, "minY": 382.75, "maxX": 556.0, "maxY": 552.0}, "class_id": 1, "box_caption": "DRONE 0.010", "scores": {"class_score": 0.01044464111328125}, "domain": "pixel"}, {"position": {"minX": -21.625, "minY": 365.75, "maxX": 376.5, "maxY": 430.25}, "class_id": 1, "box_caption": "DRONE 0.010", "scores": {"class_score": 0.010345458984375}, "domain": "pixel"}, {"position": {"minX": 415.75, "minY": 406.0, "maxX": 550.5, "maxY": 588.0}, "class_id": 1, "box_caption": "DRONE 0.010", "scores": {"class_score": 0.01032257080078125}, "domain": "pixel"}, {"position": {"minX": 519.5, "minY": 7.5, "maxX": 716.5, "maxY": 193.0}, "class_id": 1, "box_caption": "DRONE 0.010", "scores": {"class_score": 0.01027679443359375}, "domain": "pixel"}, {"position": {"minX": 63.75, "minY": 275.5, "maxX": 557.0, "maxY": 706.5}, "class_id": 1, "box_caption": "DRONE 0.010", "scores": {"class_score": 0.01026153564453125}, "domain": "pixel"}, {"position": {"minX": 360.75, "minY": 463.5, "maxX": 484.25, "maxY": 675.5}, "class_id": 1, "box_caption": "DRONE 0.010", "scores": {"class_score": 0.01025390625}, "domain": "pixel"}, {"position": {"minX": -63.3125, "minY": 333.75, "maxX": 221.5, "maxY": 370.75}, "class_id": 1, "box_caption": "DRONE 0.010", "scores": {"class_score": 0.010223388671875}, "domain": "pixel"}, {"position": {"minX": 497.0, "minY": 386.0, "maxX": 673.0, "maxY": 474.0}, "class_id": 1, "box_caption": "DRONE 0.010", "scores": {"class_score": 0.0101470947265625}, "domain": "pixel"}, {"position": {"minX": 470.25, "minY": 131.25, "maxX": 767.0, "maxY": 649.0}, "class_id": 0, "box_caption": "AIRPLANE 0.010", "scores": {"class_score": 0.0101318359375}, "domain": "pixel"}, {"position": {"minX": 613.5, "minY": 325.25, "maxX": 674.5, "maxY": 357.75}, "class_id": 1, "box_caption": "DRONE 0.010", "scores": {"class_score": 0.01006317138671875}, "domain": "pixel"}, {"position": {"minX": -136.75, "minY": 328.5, "maxX": 180.25, "maxY": 369.5}, "class_id": 1, "box_caption": "DRONE 0.010", "scores": {"class_score": 0.0100555419921875}, "domain": "pixel"}, {"position": {"minX": 364.25, "minY": 104.0, "maxX": 460.75, "maxY": 201.75}, "class_id": 1, "box_caption": "DRONE 0.010", "scores": {"class_score": 0.010009765625}, "domain": "pixel"}, {"position": {"minX": 470.25, "minY": 131.25, "maxX": 767.0, "maxY": 649.0}, "class_id": 1, "box_caption": "DRONE 0.010", "scores": {"class_score": 0.010009765625}, "domain": "pixel"}, {"position": {"minX": 543.0, "minY": 497.0, "maxX": 704.0, "maxY": 672.0}, "class_id": 0, "box_caption": "AIRPLANE 0.010", "scores": {"class_score": 0.00992584228515625}, "domain": "pixel"}, {"position": {"minX": 509.5, "minY": 421.25, "maxX": 652.5, "maxY": 499.75}, "class_id": 1, "box_caption": "DRONE 0.010", "scores": {"class_score": 0.0099029541015625}, "domain": "pixel"}, {"position": {"minX": 407.5, "minY": 48.75, "maxX": 769.5, "maxY": 760.0}, "class_id": 0, "box_caption": "AIRPLANE 0.010", "scores": {"class_score": 0.00989532470703125}, "domain": "pixel"}, {"position": {"minX": 440.0, "minY": 181.125, "maxX": 696.0, "maxY": 276.0}, "class_id": 1, "box_caption": "DRONE 0.010", "scores": {"class_score": 0.0098876953125}, "domain": "pixel"}, {"position": {"minX": 543.0, "minY": 497.0, "maxX": 704.0, "maxY": 672.0}, "class_id": 1, "box_caption": "DRONE 0.010", "scores": {"class_score": 0.009857177734375}, "domain": "pixel"}, {"position": {"minX": 87.375, "minY": -168.5, "maxX": 587.5, "maxY": 315.5}, "class_id": 1, "box_caption": "DRONE 0.010", "scores": {"class_score": 0.009735107421875}, "domain": "pixel"}, {"position": {"minX": 26.25, "minY": 350.75, "maxX": 344.75, "maxY": 375.25}, "class_id": 1, "box_caption": "DRONE 0.010", "scores": {"class_score": 0.00969696044921875}, "domain": "pixel"}, {"position": {"minX": -122.25, "minY": 156.0, "maxX": 538.0, "maxY": 624.0}, "class_id": 1, "box_caption": "DRONE 0.010", "scores": {"class_score": 0.00968170166015625}, "domain": "pixel"}, {"position": {"minX": 481.5, "minY": 426.25, "maxX": 614.5, "maxY": 500.75}, "class_id": 1, "box_caption": "DRONE 0.010", "scores": {"class_score": 0.00963592529296875}, "domain": "pixel"}, {"position": {"minX": -135.375, "minY": 302.25, "maxX": 177.375, "maxY": 334.25}, "class_id": 1, "box_caption": "DRONE 0.010", "scores": {"class_score": 0.00963592529296875}, "domain": "pixel"}, {"position": {"minX": 383.0, "minY": 176.0, "maxX": 585.0, "maxY": 351.5}, "class_id": 1, "box_caption": "DRONE 0.009", "scores": {"class_score": 0.00945281982421875}, "domain": "pixel"}, {"position": {"minX": -80.375, "minY": 324.5, "maxX": 235.375, "maxY": 451.5}, "class_id": 1, "box_caption": "DRONE 0.009", "scores": {"class_score": 0.0094451904296875}, "domain": "pixel"}, {"position": {"minX": 441.25, "minY": 19.4375, "maxX": 596.0, "maxY": 179.25}, "class_id": 1, "box_caption": "DRONE 0.009", "scores": {"class_score": 0.00942230224609375}, "domain": "pixel"}, {"position": {"minX": 386.0, "minY": 474.0, "maxX": 526.0, "maxY": 674.0}, "class_id": 1, "box_caption": "DRONE 0.009", "scores": {"class_score": 0.0094146728515625}, "domain": "pixel"}, {"position": {"minX": 69.9375, "minY": 9.875, "maxX": 259.5, "maxY": 179.875}, "class_id": 1, "box_caption": "DRONE 0.009", "scores": {"class_score": 0.009368896484375}, "domain": "pixel"}, {"position": {"minX": 7.25, "minY": 161.0, "maxX": 420.25, "maxY": 672.0}, "class_id": 1, "box_caption": "DRONE 0.009", "scores": {"class_score": 0.00934600830078125}, "domain": "pixel"}, {"position": {"minX": 534.0, "minY": 269.0, "maxX": 686.0, "maxY": 517.5}, "class_id": 1, "box_caption": "DRONE 0.009", "scores": {"class_score": 0.0093231201171875}, "domain": "pixel"}, {"position": {"minX": 531.5, "minY": 227.125, "maxX": 573.5, "maxY": 301.0}, "class_id": 1, "box_caption": "DRONE 0.009", "scores": {"class_score": 0.0092315673828125}, "domain": "pixel"}, {"position": {"minX": 198.5, "minY": -16.75, "maxX": 387.5, "maxY": 226.0}, "class_id": 1, "box_caption": "DRONE 0.009", "scores": {"class_score": 0.00921630859375}, "domain": "pixel"}, {"position": {"minX": -94.75, "minY": 559.5, "maxX": 183.75, "maxY": 659.5}, "class_id": 1, "box_caption": "DRONE 0.009", "scores": {"class_score": 0.0091705322265625}, "domain": "pixel"}, {"position": {"minX": 375.75, "minY": 173.625, "maxX": 860.0, "maxY": 662.0}, "class_id": 0, "box_caption": "AIRPLANE 0.009", "scores": {"class_score": 0.0091705322265625}, "domain": "pixel"}, {"position": {"minX": 517.0, "minY": 24.3125, "maxX": 653.0, "maxY": 175.0}, "class_id": 1, "box_caption": "DRONE 0.009", "scores": {"class_score": 0.00916290283203125}, "domain": "pixel"}, {"position": {"minX": 499.75, "minY": 92.4375, "maxX": 596.0, "maxY": 234.25}, "class_id": 1, "box_caption": "DRONE 0.009", "scores": {"class_score": 0.00911712646484375}, "domain": "pixel"}, {"position": {"minX": -287.0, "minY": -116.375, "maxX": 323.5, "maxY": 316.5}, "class_id": 1, "box_caption": "DRONE 0.009", "scores": {"class_score": 0.0090484619140625}, "domain": "pixel"}, {"position": {"minX": 238.625, "minY": -56.875, "maxX": 351.5, "maxY": 194.5}, "class_id": 1, "box_caption": "DRONE 0.009", "scores": {"class_score": 0.00904083251953125}, "domain": "pixel"}, {"position": {"minX": 526.0, "minY": 289.5, "maxX": 573.0, "maxY": 482.0}, "class_id": 0, "box_caption": "AIRPLANE 0.009", "scores": {"class_score": 0.009033203125}, "domain": "pixel"}, {"position": {"minX": -259.5, "minY": -26.125, "maxX": 715.0, "maxY": 509.5}, "class_id": 1, "box_caption": "DRONE 0.009", "scores": {"class_score": 0.00902557373046875}, "domain": "pixel"}, {"position": {"minX": 142.0, "minY": -70.9375, "maxX": 256.5, "maxY": 142.5}, "class_id": 1, "box_caption": "DRONE 0.009", "scores": {"class_score": 0.0090179443359375}, "domain": "pixel"}, {"position": {"minX": 262.5, "minY": 425.5, "maxX": 511.0, "maxY": 640.5}, "class_id": 1, "box_caption": "DRONE 0.009", "scores": {"class_score": 0.0090179443359375}, "domain": "pixel"}, {"position": {"minX": 314.0, "minY": 248.0, "maxX": 593.5, "maxY": 430.0}, "class_id": 1, "box_caption": "DRONE 0.009", "scores": {"class_score": 0.00899505615234375}, "domain": "pixel"}, {"position": {"minX": 497.75, "minY": -45.875, "maxX": 612.0, "maxY": 119.125}, "class_id": 1, "box_caption": "DRONE 0.009", "scores": {"class_score": 0.00894927978515625}, "domain": "pixel"}, {"position": {"minX": 507.25, "minY": 636.0, "maxX": 521.0, "maxY": 647.0}, "class_id": 0, "box_caption": "AIRPLANE 0.009", "scores": {"class_score": 0.00885009765625}, "domain": "pixel"}, {"position": {"minX": 98.6875, "minY": 135.0, "maxX": 342.5, "maxY": 313.25}, "class_id": 1, "box_caption": "DRONE 0.009", "scores": {"class_score": 0.00885009765625}, "domain": "pixel"}, {"position": {"minX": 337.25, "minY": 366.0, "maxX": 567.0, "maxY": 501.0}, "class_id": 1, "box_caption": "DRONE 0.009", "scores": {"class_score": 0.00885009765625}, "domain": "pixel"}, {"position": {"minX": 222.0, "minY": 98.25, "maxX": 969.0, "maxY": 766.0}, "class_id": 0, "box_caption": "AIRPLANE 0.009", "scores": {"class_score": 0.00882720947265625}, "domain": "pixel"}, {"position": {"minX": 538.0, "minY": 52.5, "maxX": 629.0, "maxY": 211.75}, "class_id": 1, "box_caption": "DRONE 0.009", "scores": {"class_score": 0.00879669189453125}, "domain": "pixel"}, {"position": {"minX": 96.875, "minY": 234.375, "maxX": 150.625, "maxY": 283.25}, "class_id": 1, "box_caption": "DRONE 0.009", "scores": {"class_score": 0.0087890625}, "domain": "pixel"}, {"position": {"minX": 402.0, "minY": 219.375, "maxX": 708.0, "maxY": 377.0}, "class_id": 1, "box_caption": "DRONE 0.009", "scores": {"class_score": 0.00878143310546875}, "domain": "pixel"}, {"position": {"minX": 640.0, "minY": 271.0, "maxX": 660.0, "maxY": 347.0}, "class_id": 1, "box_caption": "DRONE 0.009", "scores": {"class_score": 0.0087738037109375}, "domain": "pixel"}, {"position": {"minX": 505.0, "minY": 264.5, "maxX": 613.0, "maxY": 318.5}, "class_id": 0, "box_caption": "AIRPLANE 0.009", "scores": {"class_score": 0.0087738037109375}, "domain": "pixel"}, {"position": {"minX": 619.5, "minY": 268.5, "maxX": 641.5, "maxY": 345.5}, "class_id": 1, "box_caption": "DRONE 0.009", "scores": {"class_score": 0.008758544921875}, "domain": "pixel"}, {"position": {"minX": -0.5, "minY": -92.5, "maxX": 602.0, "maxY": 444.5}, "class_id": 1, "box_caption": "DRONE 0.009", "scores": {"class_score": 0.00875091552734375}, "domain": "pixel"}, {"position": {"minX": 89.5, "minY": 43.875, "maxX": 234.0, "maxY": 207.5}, "class_id": 1, "box_caption": "DRONE 0.009", "scores": {"class_score": 0.00872802734375}, "domain": "pixel"}, {"position": {"minX": 333.5, "minY": 559.5, "maxX": 658.5, "maxY": 703.5}, "class_id": 1, "box_caption": "DRONE 0.009", "scores": {"class_score": 0.00868988037109375}, "domain": "pixel"}, {"position": {"minX": -98.625, "minY": 123.75, "maxX": 276.0, "maxY": 782.0}, "class_id": 1, "box_caption": "DRONE 0.009", "scores": {"class_score": 0.00868988037109375}, "domain": "pixel"}, {"position": {"minX": -133.0, "minY": 350.0, "maxX": 176.5, "maxY": 412.5}, "class_id": 1, "box_caption": "DRONE 0.009", "scores": {"class_score": 0.0086517333984375}, "domain": "pixel"}, {"position": {"minX": 456.75, "minY": 553.5, "maxX": 590.0, "maxY": 659.5}, "class_id": 1, "box_caption": "DRONE 0.009", "scores": {"class_score": 0.00864410400390625}, "domain": "pixel"}, {"position": {"minX": 400.0, "minY": 530.0, "maxX": 728.0, "maxY": 707.0}, "class_id": 1, "box_caption": "DRONE 0.009", "scores": {"class_score": 0.008636474609375}, "domain": "pixel"}, {"position": {"minX": -16.6875, "minY": 312.0, "maxX": 235.75, "maxY": 334.5}, "class_id": 1, "box_caption": "DRONE 0.009", "scores": {"class_score": 0.00856781005859375}, "domain": "pixel"}, {"position": {"minX": 460.25, "minY": -74.5, "maxX": 582.5, "maxY": 148.75}, "class_id": 1, "box_caption": "DRONE 0.009", "scores": {"class_score": 0.008544921875}, "domain": "pixel"}, {"position": {"minX": 460.5, "minY": 275.5, "maxX": 708.5, "maxY": 390.0}, "class_id": 1, "box_caption": "DRONE 0.008", "scores": {"class_score": 0.0084686279296875}, "domain": "pixel"}, {"position": {"minX": 356.75, "minY": 72.125, "maxX": 486.75, "maxY": 177.625}, "class_id": 1, "box_caption": "DRONE 0.008", "scores": {"class_score": 0.008453369140625}, "domain": "pixel"}, {"position": {"minX": 505.0, "minY": 264.5, "maxX": 613.0, "maxY": 318.5}, "class_id": 1, "box_caption": "DRONE 0.008", "scores": {"class_score": 0.008453369140625}, "domain": "pixel"}, {"position": {"minX": 400.0, "minY": 530.0, "maxX": 728.0, "maxY": 707.0}, "class_id": 0, "box_caption": "AIRPLANE 0.008", "scores": {"class_score": 0.008453369140625}, "domain": "pixel"}, {"position": {"minX": 519.5, "minY": 521.0, "maxX": 653.5, "maxY": 611.0}, "class_id": 1, "box_caption": "DRONE 0.008", "scores": {"class_score": 0.00843048095703125}, "domain": "pixel"}, {"position": {"minX": -119.75, "minY": 270.75, "maxX": 159.0, "maxY": 305.75}, "class_id": 1, "box_caption": "DRONE 0.008", "scores": {"class_score": 0.0084075927734375}, "domain": "pixel"}, {"position": {"minX": 114.1875, "minY": 60.9375, "maxX": 271.0, "maxY": 194.0}, "class_id": 1, "box_caption": "DRONE 0.008", "scores": {"class_score": 0.00835418701171875}, "domain": "pixel"}, {"position": {"minX": -80.375, "minY": 324.5, "maxX": 235.375, "maxY": 451.5}, "class_id": 0, "box_caption": "AIRPLANE 0.008", "scores": {"class_score": 0.008331298828125}, "domain": "pixel"}, {"position": {"minX": -37.5, "minY": 177.875, "maxX": 230.5, "maxY": 337.0}, "class_id": 1, "box_caption": "DRONE 0.008", "scores": {"class_score": 0.00832366943359375}, "domain": "pixel"}, {"position": {"minX": -15.4375, "minY": 99.75, "maxX": 170.75, "maxY": 239.25}, "class_id": 0, "box_caption": "AIRPLANE 0.008", "scores": {"class_score": 0.0082855224609375}, "domain": "pixel"}, {"position": {"minX": 475.0, "minY": 482.0, "maxX": 623.0, "maxY": 574.0}, "class_id": 1, "box_caption": "DRONE 0.008", "scores": {"class_score": 0.00827789306640625}, "domain": "pixel"}, {"position": {"minX": 632.5, "minY": 239.75, "maxX": 659.5, "maxY": 312.75}, "class_id": 1, "box_caption": "DRONE 0.008", "scores": {"class_score": 0.0082244873046875}, "domain": "pixel"}, {"position": {"minX": 206.5, "minY": -72.875, "maxX": 316.5, "maxY": 147.125}, "class_id": 1, "box_caption": "DRONE 0.008", "scores": {"class_score": 0.0082244873046875}, "domain": "pixel"}, {"position": {"minX": -297.0, "minY": 83.0, "maxX": 606.0, "maxY": 701.0}, "class_id": 0, "box_caption": "AIRPLANE 0.008", "scores": {"class_score": 0.00818634033203125}, "domain": "pixel"}, {"position": {"minX": 254.25, "minY": -225.375, "maxX": 937.0, "maxY": 429.0}, "class_id": 1, "box_caption": "DRONE 0.008", "scores": {"class_score": 0.00815582275390625}, "domain": "pixel"}, {"position": {"minX": -65.25, "minY": -92.625, "maxX": 165.25, "maxY": 104.625}, "class_id": 1, "box_caption": "DRONE 0.008", "scores": {"class_score": 0.008056640625}, "domain": "pixel"}, {"position": {"minX": -63.3125, "minY": 333.75, "maxX": 221.5, "maxY": 370.75}, "class_id": 0, "box_caption": "AIRPLANE 0.008", "scores": {"class_score": 0.008056640625}, "domain": "pixel"}, {"position": {"minX": 388.75, "minY": -46.8125, "maxX": 666.0, "maxY": 64.5}, "class_id": 1, "box_caption": "DRONE 0.008", "scores": {"class_score": 0.008026123046875}, "domain": "pixel"}, {"position": {"minX": 103.8125, "minY": -87.25, "maxX": 235.5, "maxY": 155.5}, "class_id": 1, "box_caption": "DRONE 0.008", "scores": {"class_score": 0.0080108642578125}, "domain": "pixel"}, {"position": {"minX": 385.5, "minY": 78.8125, "maxX": 574.5, "maxY": 247.5}, "class_id": 1, "box_caption": "DRONE 0.008", "scores": {"class_score": 0.00800323486328125}, "domain": "pixel"}, {"position": {"minX": 58.4375, "minY": -95.875, "maxX": 214.5, "maxY": 163.375}, "class_id": 1, "box_caption": "DRONE 0.008", "scores": {"class_score": 0.00798797607421875}, "domain": "pixel"}, {"position": {"minX": 615.5, "minY": 326.75, "maxX": 639.5, "maxY": 374.75}, "class_id": 1, "box_caption": "DRONE 0.008", "scores": {"class_score": 0.00797271728515625}, "domain": "pixel"}, {"position": {"minX": 291.5, "minY": 520.5, "maxX": 368.0, "maxY": 743.5}, "class_id": 1, "box_caption": "DRONE 0.008", "scores": {"class_score": 0.0079498291015625}, "domain": "pixel"}, {"position": {"minX": 349.0, "minY": 20.8125, "maxX": 554.5, "maxY": 185.0}, "class_id": 1, "box_caption": "DRONE 0.008", "scores": {"class_score": 0.007904052734375}, "domain": "pixel"}, {"position": {"minX": 79.125, "minY": 240.25, "maxX": 135.375, "maxY": 273.75}, "class_id": 1, "box_caption": "DRONE 0.008", "scores": {"class_score": 0.00788116455078125}, "domain": "pixel"}, {"position": {"minX": -60.75, "minY": 342.75, "maxX": 288.0, "maxY": 490.75}, "class_id": 1, "box_caption": "DRONE 0.008", "scores": {"class_score": 0.00788116455078125}, "domain": "pixel"}, {"position": {"minX": 119.5, "minY": 113.5625, "maxX": 325.0, "maxY": 265.75}, "class_id": 1, "box_caption": "DRONE 0.008", "scores": {"class_score": 0.007843017578125}, "domain": "pixel"}, {"position": {"minX": 362.5, "minY": -11.75, "maxX": 740.5, "maxY": 816.0}, "class_id": 1, "box_caption": "DRONE 0.008", "scores": {"class_score": 0.00783538818359375}, "domain": "pixel"}, {"position": {"minX": 522.5, "minY": 489.0, "maxX": 591.5, "maxY": 616.0}, "class_id": 0, "box_caption": "AIRPLANE 0.008", "scores": {"class_score": 0.00782012939453125}, "domain": "pixel"}, {"position": {"minX": 284.0, "minY": -103.6875, "maxX": 966.0, "maxY": 305.0}, "class_id": 1, "box_caption": "DRONE 0.008", "scores": {"class_score": 0.007781982421875}, "domain": "pixel"}, {"position": {"minX": -1.625, "minY": 277.25, "maxX": 155.875, "maxY": 308.25}, "class_id": 1, "box_caption": "DRONE 0.008", "scores": {"class_score": 0.007709503173828125}, "domain": "pixel"}, {"position": {"minX": 546.5, "minY": 352.75, "maxX": 674.5, "maxY": 488.75}, "class_id": 1, "box_caption": "DRONE 0.008", "scores": {"class_score": 0.00769805908203125}, "domain": "pixel"}, {"position": {"minX": 127.8125, "minY": -114.0, "maxX": 339.75, "maxY": 138.625}, "class_id": 1, "box_caption": "DRONE 0.008", "scores": {"class_score": 0.007694244384765625}, "domain": "pixel"}, {"position": {"minX": 7.25, "minY": 161.0, "maxX": 420.25, "maxY": 672.0}, "class_id": 0, "box_caption": "AIRPLANE 0.008", "scores": {"class_score": 0.007686614990234375}, "domain": "pixel"}, {"position": {"minX": 313.0, "minY": 573.5, "maxX": 563.0, "maxY": 734.5}, "class_id": 0, "box_caption": "AIRPLANE 0.008", "scores": {"class_score": 0.0076751708984375}, "domain": "pixel"}, {"position": {"minX": -142.0, "minY": 163.5, "maxX": 295.25, "maxY": 945.5}, "class_id": 0, "box_caption": "AIRPLANE 0.008", "scores": {"class_score": 0.007659912109375}, "domain": "pixel"}, {"position": {"minX": 296.5, "minY": 344.75, "maxX": 606.5, "maxY": 453.25}, "class_id": 1, "box_caption": "DRONE 0.008", "scores": {"class_score": 0.007617950439453125}, "domain": "pixel"}, {"position": {"minX": -65.25, "minY": -92.625, "maxX": 165.25, "maxY": 104.625}, "class_id": 0, "box_caption": "AIRPLANE 0.008", "scores": {"class_score": 0.007598876953125}, "domain": "pixel"}, {"position": {"minX": -111.75, "minY": 147.25, "maxX": 457.25, "maxY": 834.0}, "class_id": 0, "box_caption": "AIRPLANE 0.008", "scores": {"class_score": 0.00759124755859375}, "domain": "pixel"}, {"position": {"minX": 1.0, "minY": 129.0, "maxX": 252.5, "maxY": 323.5}, "class_id": 1, "box_caption": "DRONE 0.008", "scores": {"class_score": 0.007587432861328125}, "domain": "pixel"}, {"position": {"minX": 364.0, "minY": 180.875, "maxX": 527.5, "maxY": 338.5}, "class_id": 1, "box_caption": "DRONE 0.008", "scores": {"class_score": 0.007587432861328125}, "domain": "pixel"}, {"position": {"minX": 493.0, "minY": 516.0, "maxX": 550.0, "maxY": 590.0}, "class_id": 0, "box_caption": "AIRPLANE 0.008", "scores": {"class_score": 0.007579803466796875}, "domain": "pixel"}, {"position": {"minX": 533.0, "minY": 179.5, "maxX": 572.0, "maxY": 287.5}, "class_id": 1, "box_caption": "DRONE 0.008", "scores": {"class_score": 0.00757598876953125}, "domain": "pixel"}, {"position": {"minX": 639.5, "minY": 251.0, "maxX": 652.5, "maxY": 334.5}, "class_id": 1, "box_caption": "DRONE 0.008", "scores": {"class_score": 0.007572174072265625}, "domain": "pixel"}, {"position": {"minX": 525.0, "minY": -39.625, "maxX": 649.0, "maxY": 112.875}, "class_id": 1, "box_caption": "DRONE 0.008", "scores": {"class_score": 0.0075531005859375}, "domain": "pixel"}, {"position": {"minX": 430.75, "minY": 99.0, "maxX": 884.0, "maxY": 707.0}, "class_id": 1, "box_caption": "DRONE 0.008", "scores": {"class_score": 0.007537841796875}, "domain": "pixel"}, {"position": {"minX": -70.25, "minY": 347.5, "maxX": 149.5, "maxY": 877.5}, "class_id": 1, "box_caption": "DRONE 0.007", "scores": {"class_score": 0.007495880126953125}, "domain": "pixel"}, {"position": {"minX": 131.25, "minY": 18.6875, "maxX": 330.5, "maxY": 173.75}, "class_id": 1, "box_caption": "DRONE 0.007", "scores": {"class_score": 0.007472991943359375}, "domain": "pixel"}, {"position": {"minX": 521.0, "minY": 364.25, "maxX": 570.0, "maxY": 467.75}, "class_id": 0, "box_caption": "AIRPLANE 0.007", "scores": {"class_score": 0.0074615478515625}, "domain": "pixel"}, {"position": {"minX": 620.5, "minY": 249.75, "maxX": 636.5, "maxY": 297.75}, "class_id": 1, "box_caption": "DRONE 0.007", "scores": {"class_score": 0.007450103759765625}, "domain": "pixel"}, {"position": {"minX": 185.5, "minY": 552.5, "maxX": 684.5, "maxY": 689.5}, "class_id": 0, "box_caption": "AIRPLANE 0.007", "scores": {"class_score": 0.00743865966796875}, "domain": "pixel"}, {"position": {"minX": 507.25, "minY": 636.0, "maxX": 521.0, "maxY": 647.0}, "class_id": 1, "box_caption": "DRONE 0.007", "scores": {"class_score": 0.0074005126953125}, "domain": "pixel"}, {"position": {"minX": 509.0, "minY": 277.0, "maxX": 712.0, "maxY": 437.0}, "class_id": 0, "box_caption": "AIRPLANE 0.007", "scores": {"class_score": 0.007389068603515625}, "domain": "pixel"}, {"position": {"minX": 561.5, "minY": 436.0, "maxX": 593.5, "maxY": 464.0}, "class_id": 1, "box_caption": "DRONE 0.007", "scores": {"class_score": 0.00738525390625}, "domain": "pixel"}, {"position": {"minX": 343.25, "minY": 166.25, "maxX": 468.75, "maxY": 403.75}, "class_id": 1, "box_caption": "DRONE 0.007", "scores": {"class_score": 0.0073699951171875}, "domain": "pixel"}, {"position": {"minX": 26.25, "minY": 51.75, "maxX": 171.0, "maxY": 201.125}, "class_id": 1, "box_caption": "DRONE 0.007", "scores": {"class_score": 0.007358551025390625}, "domain": "pixel"}, {"position": {"minX": 68.6875, "minY": 55.625, "maxX": 192.25, "maxY": 197.375}, "class_id": 1, "box_caption": "DRONE 0.007", "scores": {"class_score": 0.007350921630859375}, "domain": "pixel"}, {"position": {"minX": -51.0, "minY": 38.0, "maxX": 548.5, "maxY": 588.0}, "class_id": 0, "box_caption": "AIRPLANE 0.007", "scores": {"class_score": 0.007335662841796875}, "domain": "pixel"}, {"position": {"minX": 535.0, "minY": -47.53125, "maxX": 705.0, "maxY": 118.25}, "class_id": 1, "box_caption": "DRONE 0.007", "scores": {"class_score": 0.007328033447265625}, "domain": "pixel"}, {"position": {"minX": -35.5, "minY": 216.625, "maxX": 639.5, "maxY": 570.0}, "class_id": 1, "box_caption": "DRONE 0.007", "scores": {"class_score": 0.007328033447265625}, "domain": "pixel"}, {"position": {"minX": 502.75, "minY": 299.25, "maxX": 598.0, "maxY": 417.75}, "class_id": 0, "box_caption": "AIRPLANE 0.007", "scores": {"class_score": 0.00731658935546875}, "domain": "pixel"}, {"position": {"minX": 457.25, "minY": 320.25, "maxX": 603.0, "maxY": 334.25}, "class_id": 1, "box_caption": "DRONE 0.007", "scores": {"class_score": 0.007289886474609375}, "domain": "pixel"}, {"position": {"minX": -26.5625, "minY": 35.75, "maxX": 188.25, "maxY": 239.5}, "class_id": 0, "box_caption": "AIRPLANE 0.007", "scores": {"class_score": 0.00728607177734375}, "domain": "pixel"}, {"position": {"minX": 366.75, "minY": 334.25, "maxX": 570.0, "maxY": 383.25}, "class_id": 1, "box_caption": "DRONE 0.007", "scores": {"class_score": 0.0072784423828125}, "domain": "pixel"}, {"position": {"minX": 492.25, "minY": 37.0, "maxX": 612.0, "maxY": 158.25}, "class_id": 1, "box_caption": "DRONE 0.007", "scores": {"class_score": 0.007274627685546875}, "domain": "pixel"}, {"position": {"minX": 510.5, "minY": 482.5, "maxX": 815.5, "maxY": 692.5}, "class_id": 0, "box_caption": "AIRPLANE 0.007", "scores": {"class_score": 0.0072479248046875}, "domain": "pixel"}, {"position": {"minX": 49.6875, "minY": 189.75, "maxX": 268.5, "maxY": 326.75}, "class_id": 1, "box_caption": "DRONE 0.007", "scores": {"class_score": 0.007244110107421875}, "domain": "pixel"}, {"position": {"minX": 431.0, "minY": 311.5, "maxX": 573.5, "maxY": 341.0}, "class_id": 1, "box_caption": "DRONE 0.007", "scores": {"class_score": 0.007244110107421875}, "domain": "pixel"}, {"position": {"minX": -101.875, "minY": 388.25, "maxX": 210.625, "maxY": 513.5}, "class_id": 0, "box_caption": "AIRPLANE 0.007", "scores": {"class_score": 0.00724029541015625}, "domain": "pixel"}, {"position": {"minX": 559.0, "minY": 377.0, "maxX": 736.0, "maxY": 436.5}, "class_id": 1, "box_caption": "DRONE 0.007", "scores": {"class_score": 0.007232666015625}, "domain": "pixel"}, {"position": {"minX": 63.375, "minY": 142.25, "maxX": 360.5, "maxY": 831.0}, "class_id": 0, "box_caption": "AIRPLANE 0.007", "scores": {"class_score": 0.007232666015625}, "domain": "pixel"}, {"position": {"minX": 431.5, "minY": 184.0, "maxX": 663.5, "maxY": 335.5}, "class_id": 1, "box_caption": "DRONE 0.007", "scores": {"class_score": 0.007183074951171875}, "domain": "pixel"}, {"position": {"minX": -127.4375, "minY": 323.25, "maxX": 222.25, "maxY": 381.75}, "class_id": 0, "box_caption": "AIRPLANE 0.007", "scores": {"class_score": 0.00716400146484375}, "domain": "pixel"}, {"position": {"minX": 562.0, "minY": 434.25, "maxX": 592.0, "maxY": 445.75}, "class_id": 1, "box_caption": "DRONE 0.007", "scores": {"class_score": 0.0071258544921875}, "domain": "pixel"}, {"position": {"minX": 539.5, "minY": 223.125, "maxX": 589.5, "maxY": 308.5}, "class_id": 1, "box_caption": "DRONE 0.007", "scores": {"class_score": 0.00711822509765625}, "domain": "pixel"}, {"position": {"minX": 127.1875, "minY": 170.5, "maxX": 310.25, "maxY": 343.5}, "class_id": 1, "box_caption": "DRONE 0.007", "scores": {"class_score": 0.007110595703125}, "domain": "pixel"}, {"position": {"minX": 513.5, "minY": 439.5, "maxX": 649.5, "maxY": 549.0}, "class_id": 1, "box_caption": "DRONE 0.007", "scores": {"class_score": 0.007110595703125}, "domain": "pixel"}, {"position": {"minX": 621.5, "minY": 249.5, "maxX": 635.5, "maxY": 331.5}, "class_id": 1, "box_caption": "DRONE 0.007", "scores": {"class_score": 0.00710296630859375}, "domain": "pixel"}, {"position": {"minX": 306.25, "minY": -64.875, "maxX": 792.0, "maxY": 540.0}, "class_id": 0, "box_caption": "AIRPLANE 0.007", "scores": {"class_score": 0.007099151611328125}, "domain": "pixel"}, {"position": {"minX": 501.25, "minY": 439.75, "maxX": 767.0, "maxY": 801.0}, "class_id": 0, "box_caption": "AIRPLANE 0.007", "scores": {"class_score": 0.007080078125}, "domain": "pixel"}, {"position": {"minX": 132.875, "minY": -81.0, "maxX": 551.5, "maxY": 170.625}, "class_id": 1, "box_caption": "DRONE 0.007", "scores": {"class_score": 0.007080078125}, "domain": "pixel"}, {"position": {"minX": 174.5, "minY": 50.625, "maxX": 351.5, "maxY": 203.5}, "class_id": 1, "box_caption": "DRONE 0.007", "scores": {"class_score": 0.00707244873046875}, "domain": "pixel"}, {"position": {"minX": 513.0, "minY": 62.375, "maxX": 590.0, "maxY": 200.875}, "class_id": 1, "box_caption": "DRONE 0.007", "scores": {"class_score": 0.00707244873046875}, "domain": "pixel"}, {"position": {"minX": 623.0, "minY": 275.5, "maxX": 638.0, "maxY": 367.0}, "class_id": 0, "box_caption": "AIRPLANE 0.007", "scores": {"class_score": 0.007068634033203125}, "domain": "pixel"}, {"position": {"minX": -125.375, "minY": 87.75, "maxX": 353.5, "maxY": 949.0}, "class_id": 1, "box_caption": "DRONE 0.007", "scores": {"class_score": 0.007068634033203125}, "domain": "pixel"}, {"position": {"minX": 343.25, "minY": 530.0, "maxX": 519.0, "maxY": 657.0}, "class_id": 1, "box_caption": "DRONE 0.007", "scores": {"class_score": 0.007061004638671875}, "domain": "pixel"}, {"position": {"minX": 482.25, "minY": 431.0, "maxX": 615.5, "maxY": 553.5}, "class_id": 1, "box_caption": "DRONE 0.007", "scores": {"class_score": 0.007053375244140625}, "domain": "pixel"}, {"position": {"minX": 144.125, "minY": 518.0, "maxX": 255.375, "maxY": 595.0}, "class_id": 1, "box_caption": "DRONE 0.007", "scores": {"class_score": 0.007038116455078125}, "domain": "pixel"}, {"position": {"minX": -117.9375, "minY": 373.25, "maxX": 165.0, "maxY": 454.25}, "class_id": 1, "box_caption": "DRONE 0.007", "scores": {"class_score": 0.007038116455078125}, "domain": "pixel"}, {"position": {"minX": 168.125, "minY": -151.625, "maxX": 494.5, "maxY": 379.0}, "class_id": 1, "box_caption": "DRONE 0.007", "scores": {"class_score": 0.007038116455078125}, "domain": "pixel"}, {"position": {"minX": 148.0, "minY": 224.25, "maxX": 376.0, "maxY": 424.75}, "class_id": 1, "box_caption": "DRONE 0.007", "scores": {"class_score": 0.007022857666015625}, "domain": "pixel"}, {"position": {"minX": -288.75, "minY": 496.5, "maxX": 341.25, "maxY": 798.5}, "class_id": 1, "box_caption": "DRONE 0.007", "scores": {"class_score": 0.007007598876953125}, "domain": "pixel"}, {"position": {"minX": 490.5, "minY": 78.375, "maxX": 736.5, "maxY": 235.125}, "class_id": 1, "box_caption": "DRONE 0.007", "scores": {"class_score": 0.006984710693359375}, "domain": "pixel"}, {"position": {"minX": 317.5, "minY": 92.375, "maxX": 547.5, "maxY": 208.375}, "class_id": 0, "box_caption": "AIRPLANE 0.007", "scores": {"class_score": 0.006954193115234375}, "domain": "pixel"}, {"position": {"minX": 465.0, "minY": 36.4375, "maxX": 769.0, "maxY": 217.75}, "class_id": 1, "box_caption": "DRONE 0.007", "scores": {"class_score": 0.0069427490234375}, "domain": "pixel"}, {"position": {"minX": 84.25, "minY": 135.25, "maxX": 465.25, "maxY": 842.0}, "class_id": 1, "box_caption": "DRONE 0.007", "scores": {"class_score": 0.006927490234375}, "domain": "pixel"}, {"position": {"minX": 94.75, "minY": 254.5, "maxX": 147.375, "maxY": 294.0}, "class_id": 1, "box_caption": "DRONE 0.007", "scores": {"class_score": 0.006900787353515625}, "domain": "pixel"}, {"position": {"minX": 265.5, "minY": 529.0, "maxX": 468.5, "maxY": 732.0}, "class_id": 1, "box_caption": "DRONE 0.007", "scores": {"class_score": 0.006900787353515625}, "domain": "pixel"}, {"position": {"minX": 444.5, "minY": -89.75, "maxX": 674.5, "maxY": 116.75}, "class_id": 1, "box_caption": "DRONE 0.007", "scores": {"class_score": 0.006877899169921875}, "domain": "pixel"}, {"position": {"minX": 401.5, "minY": 305.75, "maxX": 534.5, "maxY": 345.25}, "class_id": 1, "box_caption": "DRONE 0.007", "scores": {"class_score": 0.006877899169921875}, "domain": "pixel"}, {"position": {"minX": 559.0, "minY": 254.625, "maxX": 732.0, "maxY": 590.0}, "class_id": 0, "box_caption": "AIRPLANE 0.007", "scores": {"class_score": 0.006866455078125}, "domain": "pixel"}, {"position": {"minX": -3.984375, "minY": 220.875, "maxX": 35.125, "maxY": 269.5}, "class_id": 1, "box_caption": "DRONE 0.007", "scores": {"class_score": 0.006862640380859375}, "domain": "pixel"}, {"position": {"minX": -95.25, "minY": 321.0, "maxX": 244.75, "maxY": 520.5}, "class_id": 0, "box_caption": "AIRPLANE 0.007", "scores": {"class_score": 0.0068511962890625}, "domain": "pixel"}, {"position": {"minX": 333.25, "minY": 36.0625, "maxX": 510.75, "maxY": 159.75}, "class_id": 1, "box_caption": "DRONE 0.007", "scores": {"class_score": 0.006816864013671875}, "domain": "pixel"}, {"position": {"minX": 476.0, "minY": 546.5, "maxX": 567.0, "maxY": 625.5}, "class_id": 0, "box_caption": "AIRPLANE 0.007", "scores": {"class_score": 0.006778717041015625}, "domain": "pixel"}, {"position": {"minX": 34.1875, "minY": 282.0, "maxX": 183.25, "maxY": 306.0}, "class_id": 1, "box_caption": "DRONE 0.007", "scores": {"class_score": 0.0067596435546875}, "domain": "pixel"}, {"position": {"minX": 625.0, "minY": 186.125, "maxX": 666.0, "maxY": 265.25}, "class_id": 1, "box_caption": "DRONE 0.007", "scores": {"class_score": 0.006744384765625}, "domain": "pixel"}, {"position": {"minX": 544.5, "minY": 211.75, "maxX": 574.5, "maxY": 301.25}, "class_id": 1, "box_caption": "DRONE 0.007", "scores": {"class_score": 0.006744384765625}, "domain": "pixel"}, {"position": {"minX": 566.5, "minY": 325.25, "maxX": 736.5, "maxY": 412.25}, "class_id": 1, "box_caption": "DRONE 0.007", "scores": {"class_score": 0.0067138671875}, "domain": "pixel"}, {"position": {"minX": -15.75, "minY": 354.75, "maxX": 372.25, "maxY": 494.75}, "class_id": 0, "box_caption": "AIRPLANE 0.007", "scores": {"class_score": 0.0067138671875}, "domain": "pixel"}, {"position": {"minX": 144.375, "minY": 116.75, "maxX": 335.5, "maxY": 787.0}, "class_id": 0, "box_caption": "AIRPLANE 0.007", "scores": {"class_score": 0.00670623779296875}, "domain": "pixel"}, {"position": {"minX": 293.5, "minY": 94.25, "maxX": 456.5, "maxY": 273.25}, "class_id": 1, "box_caption": "DRONE 0.007", "scores": {"class_score": 0.00667572021484375}, "domain": "pixel"}, {"position": {"minX": 349.5, "minY": 343.5, "maxX": 528.0, "maxY": 381.0}, "class_id": 1, "box_caption": "DRONE 0.007", "scores": {"class_score": 0.006656646728515625}, "domain": "pixel"}, {"position": {"minX": 76.9375, "minY": 256.0, "maxX": 134.5, "maxY": 290.0}, "class_id": 1, "box_caption": "DRONE 0.007", "scores": {"class_score": 0.00665283203125}, "domain": "pixel"}, {"position": {"minX": 216.625, "minY": 91.5, "maxX": 626.5, "maxY": 533.5}, "class_id": 0, "box_caption": "AIRPLANE 0.007", "scores": {"class_score": 0.00665283203125}, "domain": "pixel"}, {"position": {"minX": 327.0, "minY": 65.125, "maxX": 427.5, "maxY": 239.125}, "class_id": 1, "box_caption": "DRONE 0.007", "scores": {"class_score": 0.006603240966796875}, "domain": "pixel"}, {"position": {"minX": 544.5, "minY": 211.75, "maxX": 574.5, "maxY": 301.25}, "class_id": 0, "box_caption": "AIRPLANE 0.007", "scores": {"class_score": 0.00659942626953125}, "domain": "pixel"}, {"position": {"minX": 79.625, "minY": 275.75, "maxX": 127.125, "maxY": 303.75}, "class_id": 1, "box_caption": "DRONE 0.007", "scores": {"class_score": 0.00658416748046875}, "domain": "pixel"}, {"position": {"minX": 457.25, "minY": 320.25, "maxX": 603.0, "maxY": 334.25}, "class_id": 0, "box_caption": "AIRPLANE 0.007", "scores": {"class_score": 0.006572723388671875}, "domain": "pixel"}, {"position": {"minX": 438.75, "minY": 553.0, "maxX": 703.0, "maxY": 749.0}, "class_id": 0, "box_caption": "AIRPLANE 0.007", "scores": {"class_score": 0.006572723388671875}, "domain": "pixel"}, {"position": {"minX": 96.875, "minY": 216.875, "maxX": 150.625, "maxY": 270.0}, "class_id": 1, "box_caption": "DRONE 0.007", "scores": {"class_score": 0.006565093994140625}, "domain": "pixel"}, {"position": {"minX": 100.375, "minY": 200.625, "maxX": 143.375, "maxY": 253.625}, "class_id": 1, "box_caption": "DRONE 0.007", "scores": {"class_score": 0.006549835205078125}, "domain": "pixel"}, {"position": {"minX": 263.5, "minY": -102.3125, "maxX": 381.5, "maxY": 190.25}, "class_id": 1, "box_caption": "DRONE 0.007", "scores": {"class_score": 0.006549835205078125}, "domain": "pixel"}, {"position": {"minX": 44.0, "minY": 106.75, "maxX": 316.75, "maxY": 796.0}, "class_id": 1, "box_caption": "DRONE 0.007", "scores": {"class_score": 0.006549835205078125}, "domain": "pixel"}, {"position": {"minX": 630.0, "minY": 353.0, "maxX": 655.0, "maxY": 395.5}, "class_id": 1, "box_caption": "DRONE 0.007", "scores": {"class_score": 0.0065460205078125}, "domain": "pixel"}, {"position": {"minX": 117.4375, "minY": 318.0, "maxX": 354.5, "maxY": 907.0}, "class_id": 0, "box_caption": "AIRPLANE 0.007", "scores": {"class_score": 0.006534576416015625}, "domain": "pixel"}, {"position": {"minX": 476.5, "minY": 540.0, "maxX": 653.5, "maxY": 655.0}, "class_id": 1, "box_caption": "DRONE 0.007", "scores": {"class_score": 0.006511688232421875}, "domain": "pixel"}, {"position": {"minX": 123.25, "minY": 206.5, "maxX": 260.25, "maxY": 381.0}, "class_id": 1, "box_caption": "DRONE 0.007", "scores": {"class_score": 0.00650787353515625}, "domain": "pixel"}, {"position": {"minX": 554.5, "minY": 432.5, "maxX": 584.5, "maxY": 450.0}, "class_id": 1, "box_caption": "DRONE 0.007", "scores": {"class_score": 0.006500244140625}, "domain": "pixel"}, {"position": {"minX": 235.75, "minY": -77.875, "maxX": 416.25, "maxY": 218.625}, "class_id": 1, "box_caption": "DRONE 0.006", "scores": {"class_score": 0.006496429443359375}, "domain": "pixel"}, {"position": {"minX": 41.625, "minY": 24.75, "maxX": 223.875, "maxY": 163.75}, "class_id": 1, "box_caption": "DRONE 0.006", "scores": {"class_score": 0.006496429443359375}, "domain": "pixel"}, {"position": {"minX": 372.0, "minY": 569.0, "maxX": 668.0, "maxY": 674.0}, "class_id": 0, "box_caption": "AIRPLANE 0.006", "scores": {"class_score": 0.00647735595703125}, "domain": "pixel"}, {"position": {"minX": 144.375, "minY": 116.75, "maxX": 335.5, "maxY": 787.0}, "class_id": 1, "box_caption": "DRONE 0.006", "scores": {"class_score": 0.0064697265625}, "domain": "pixel"}, {"position": {"minX": 85.375, "minY": 206.75, "maxX": 120.875, "maxY": 246.25}, "class_id": 1, "box_caption": "DRONE 0.006", "scores": {"class_score": 0.006450653076171875}, "domain": "pixel"}, {"position": {"minX": -51.625, "minY": 212.75, "maxX": 251.625, "maxY": 433.25}, "class_id": 1, "box_caption": "DRONE 0.006", "scores": {"class_score": 0.006435394287109375}, "domain": "pixel"}, {"position": {"minX": -18.875, "minY": -114.125, "maxX": 241.875, "maxY": 137.875}, "class_id": 1, "box_caption": "DRONE 0.006", "scores": {"class_score": 0.0064239501953125}, "domain": "pixel"}, {"position": {"minX": 541.5, "minY": 531.5, "maxX": 654.5, "maxY": 631.5}, "class_id": 0, "box_caption": "AIRPLANE 0.006", "scores": {"class_score": 0.006397247314453125}, "domain": "pixel"}, {"position": {"minX": 130.5, "minY": 91.5, "maxX": 318.0, "maxY": 224.5}, "class_id": 1, "box_caption": "DRONE 0.006", "scores": {"class_score": 0.006366729736328125}, "domain": "pixel"}, {"position": {"minX": 489.0, "minY": 468.0, "maxX": 685.0, "maxY": 586.0}, "class_id": 1, "box_caption": "DRONE 0.006", "scores": {"class_score": 0.00634765625}, "domain": "pixel"}, {"position": {"minX": -38.5, "minY": 201.75, "maxX": 387.0, "maxY": 843.0}, "class_id": 1, "box_caption": "DRONE 0.006", "scores": {"class_score": 0.006336212158203125}, "domain": "pixel"}, {"position": {"minX": 615.0, "minY": 355.25, "maxX": 634.0, "maxY": 381.75}, "class_id": 1, "box_caption": "DRONE 0.006", "scores": {"class_score": 0.006320953369140625}, "domain": "pixel"}, {"position": {"minX": 509.0, "minY": 395.0, "maxX": 539.0, "maxY": 454.0}, "class_id": 0, "box_caption": "AIRPLANE 0.006", "scores": {"class_score": 0.006317138671875}, "domain": "pixel"}, {"position": {"minX": 450.5, "minY": 499.75, "maxX": 516.0, "maxY": 610.0}, "class_id": 0, "box_caption": "AIRPLANE 0.006", "scores": {"class_score": 0.006317138671875}, "domain": "pixel"}, {"position": {"minX": -14.4375, "minY": -62.0, "maxX": 161.0, "maxY": 130.625}, "class_id": 1, "box_caption": "DRONE 0.006", "scores": {"class_score": 0.006259918212890625}, "domain": "pixel"}, {"position": {"minX": 547.0, "minY": 326.25, "maxX": 616.0, "maxY": 516.0}, "class_id": 0, "box_caption": "AIRPLANE 0.006", "scores": {"class_score": 0.00623321533203125}, "domain": "pixel"}, {"position": {"minX": 629.5, "minY": 216.625, "maxX": 662.5, "maxY": 299.5}, "class_id": 1, "box_caption": "DRONE 0.006", "scores": {"class_score": 0.006175994873046875}, "domain": "pixel"}, {"position": {"minX": -43.625, "minY": 382.0, "maxX": 216.625, "maxY": 579.5}, "class_id": 0, "box_caption": "AIRPLANE 0.006", "scores": {"class_score": 0.00617218017578125}, "domain": "pixel"}, {"position": {"minX": 627.0, "minY": 375.25, "maxX": 655.0, "maxY": 406.75}, "class_id": 1, "box_caption": "DRONE 0.006", "scores": {"class_score": 0.006168365478515625}, "domain": "pixel"}, {"position": {"minX": -105.875, "minY": 84.8125, "maxX": 200.625, "maxY": 246.25}, "class_id": 0, "box_caption": "AIRPLANE 0.006", "scores": {"class_score": 0.006168365478515625}, "domain": "pixel"}, {"position": {"minX": 278.5, "minY": 445.0, "maxX": 441.0, "maxY": 695.0}, "class_id": 1, "box_caption": "DRONE 0.006", "scores": {"class_score": 0.00616455078125}, "domain": "pixel"}, {"position": {"minX": 544.5, "minY": 33.375, "maxX": 687.5, "maxY": 293.0}, "class_id": 1, "box_caption": "DRONE 0.006", "scores": {"class_score": 0.006160736083984375}, "domain": "pixel"}, {"position": {"minX": -2.328125, "minY": 203.625, "maxX": 33.5, "maxY": 255.375}, "class_id": 1, "box_caption": "DRONE 0.006", "scores": {"class_score": 0.00615692138671875}, "domain": "pixel"}, {"position": {"minX": 321.5, "minY": 538.0, "maxX": 555.5, "maxY": 705.0}, "class_id": 1, "box_caption": "DRONE 0.006", "scores": {"class_score": 0.00611114501953125}, "domain": "pixel"}, {"position": {"minX": 96.25, "minY": 276.75, "maxX": 140.625, "maxY": 305.25}, "class_id": 1, "box_caption": "DRONE 0.006", "scores": {"class_score": 0.006099700927734375}, "domain": "pixel"}, {"position": {"minX": 617.5, "minY": 294.0, "maxX": 639.5, "maxY": 379.0}, "class_id": 0, "box_caption": "AIRPLANE 0.006", "scores": {"class_score": 0.006092071533203125}, "domain": "pixel"}, {"position": {"minX": -130.75, "minY": -297.0, "maxX": 680.0, "maxY": 446.5}, "class_id": 1, "box_caption": "DRONE 0.006", "scores": {"class_score": 0.0060882568359375}, "domain": "pixel"}, {"position": {"minX": 125.625, "minY": -39.75, "maxX": 449.5, "maxY": 590.0}, "class_id": 0, "box_caption": "AIRPLANE 0.006", "scores": {"class_score": 0.0060882568359375}, "domain": "pixel"}, {"position": {"minX": -5.71875, "minY": 233.625, "maxX": 37.28125, "maxY": 287.0}, "class_id": 1, "box_caption": "DRONE 0.006", "scores": {"class_score": 0.006072998046875}, "domain": "pixel"}, {"position": {"minX": 241.875, "minY": 246.375, "maxX": 534.0, "maxY": 470.5}, "class_id": 1, "box_caption": "DRONE 0.006", "scores": {"class_score": 0.00606536865234375}, "domain": "pixel"}, {"position": {"minX": -115.625, "minY": 225.875, "maxX": 154.125, "maxY": 285.75}, "class_id": 1, "box_caption": "DRONE 0.006", "scores": {"class_score": 0.006061553955078125}, "domain": "pixel"}, {"position": {"minX": 497.0, "minY": -57.5, "maxX": 738.0, "maxY": 190.25}, "class_id": 1, "box_caption": "DRONE 0.006", "scores": {"class_score": 0.006053924560546875}, "domain": "pixel"}, {"position": {"minX": 37.84375, "minY": 65.375, "maxX": 157.375, "maxY": 250.875}, "class_id": 1, "box_caption": "DRONE 0.006", "scores": {"class_score": 0.006046295166015625}, "domain": "pixel"}, {"position": {"minX": 430.5, "minY": -72.8125, "maxX": 546.0, "maxY": 149.5}, "class_id": 1, "box_caption": "DRONE 0.006", "scores": {"class_score": 0.00603485107421875}, "domain": "pixel"}, {"position": {"minX": 82.0, "minY": 354.25, "maxX": 543.5, "maxY": 360.25}, "class_id": 0, "box_caption": "AIRPLANE 0.006", "scores": {"class_score": 0.006031036376953125}, "domain": "pixel"}, {"position": {"minX": -105.875, "minY": 84.8125, "maxX": 200.625, "maxY": 246.25}, "class_id": 1, "box_caption": "DRONE 0.006", "scores": {"class_score": 0.00601959228515625}, "domain": "pixel"}, {"position": {"minX": 458.0, "minY": 350.0, "maxX": 595.0, "maxY": 373.0}, "class_id": 0, "box_caption": "AIRPLANE 0.006", "scores": {"class_score": 0.00601959228515625}, "domain": "pixel"}, {"position": {"minX": 180.125, "minY": 323.5, "maxX": 508.5, "maxY": 332.5}, "class_id": 1, "box_caption": "DRONE 0.006", "scores": {"class_score": 0.006008148193359375}, "domain": "pixel"}, {"position": {"minX": -40.125, "minY": 545.5, "maxX": 150.125, "maxY": 630.5}, "class_id": 0, "box_caption": "AIRPLANE 0.006", "scores": {"class_score": 0.005992889404296875}, "domain": "pixel"}, {"position": {"minX": -360.5, "minY": -403.5, "maxX": 517.0, "maxY": 542.5}, "class_id": 0, "box_caption": "AIRPLANE 0.006", "scores": {"class_score": 0.00595855712890625}, "domain": "pixel"}, {"position": {"minX": 204.5, "minY": -127.625, "maxX": 387.5, "maxY": 161.125}, "class_id": 1, "box_caption": "DRONE 0.006", "scores": {"class_score": 0.005947113037109375}, "domain": "pixel"}, {"position": {"minX": -259.5, "minY": -26.125, "maxX": 715.0, "maxY": 509.5}, "class_id": 0, "box_caption": "AIRPLANE 0.006", "scores": {"class_score": 0.00594329833984375}, "domain": "pixel"}, {"position": {"minX": 129.25, "minY": 519.0, "maxX": 333.5, "maxY": 596.0}, "class_id": 1, "box_caption": "DRONE 0.006", "scores": {"class_score": 0.005931854248046875}, "domain": "pixel"}, {"position": {"minX": 287.0, "minY": -2.4375, "maxX": 485.0, "maxY": 194.0}, "class_id": 1, "box_caption": "DRONE 0.006", "scores": {"class_score": 0.00592803955078125}, "domain": "pixel"}, {"position": {"minX": 388.75, "minY": 414.0, "maxX": 572.0, "maxY": 521.0}, "class_id": 0, "box_caption": "AIRPLANE 0.006", "scores": {"class_score": 0.005924224853515625}, "domain": "pixel"}, {"position": {"minX": 501.25, "minY": 439.75, "maxX": 767.0, "maxY": 801.0}, "class_id": 1, "box_caption": "DRONE 0.006", "scores": {"class_score": 0.00589752197265625}, "domain": "pixel"}, {"position": {"minX": 69.375, "minY": -109.75, "maxX": 276.0, "maxY": 140.375}, "class_id": 1, "box_caption": "DRONE 0.006", "scores": {"class_score": 0.005886077880859375}, "domain": "pixel"}, {"position": {"minX": 492.5, "minY": 352.5, "maxX": 553.5, "maxY": 437.5}, "class_id": 0, "box_caption": "AIRPLANE 0.006", "scores": {"class_score": 0.00588226318359375}, "domain": "pixel"}, {"position": {"minX": 533.0, "minY": 270.75, "maxX": 705.0, "maxY": 364.25}, "class_id": 0, "box_caption": "AIRPLANE 0.006", "scores": {"class_score": 0.005878448486328125}, "domain": "pixel"}, {"position": {"minX": 509.0, "minY": 277.0, "maxX": 712.0, "maxY": 437.0}, "class_id": 1, "box_caption": "DRONE 0.006", "scores": {"class_score": 0.005870819091796875}, "domain": "pixel"}, {"position": {"minX": 524.5, "minY": 164.5, "maxX": 573.5, "maxY": 268.5}, "class_id": 1, "box_caption": "DRONE 0.006", "scores": {"class_score": 0.005863189697265625}, "domain": "pixel"}, {"position": {"minX": 150.125, "minY": 209.375, "maxX": 516.0, "maxY": 644.0}, "class_id": 1, "box_caption": "DRONE 0.006", "scores": {"class_score": 0.00585174560546875}, "domain": "pixel"}, {"position": {"minX": 619.5, "minY": 268.5, "maxX": 641.5, "maxY": 345.5}, "class_id": 0, "box_caption": "AIRPLANE 0.006", "scores": {"class_score": 0.00583648681640625}, "domain": "pixel"}, {"position": {"minX": -33.6875, "minY": -37.1875, "maxX": 198.75, "maxY": 250.0}, "class_id": 1, "box_caption": "DRONE 0.006", "scores": {"class_score": 0.00583648681640625}, "domain": "pixel"}, {"position": {"minX": -27.5625, "minY": 130.75, "maxX": 161.25, "maxY": 323.0}, "class_id": 1, "box_caption": "DRONE 0.006", "scores": {"class_score": 0.005832672119140625}, "domain": "pixel"}, {"position": {"minX": 167.125, "minY": 184.0, "maxX": 343.0, "maxY": 398.0}, "class_id": 1, "box_caption": "DRONE 0.006", "scores": {"class_score": 0.005825042724609375}, "domain": "pixel"}, {"position": {"minX": 523.5, "minY": 283.25, "maxX": 653.5, "maxY": 364.75}, "class_id": 1, "box_caption": "DRONE 0.006", "scores": {"class_score": 0.005825042724609375}, "domain": "pixel"}, {"position": {"minX": -43.6875, "minY": 341.75, "maxX": 266.25, "maxY": 363.25}, "class_id": 0, "box_caption": "AIRPLANE 0.006", "scores": {"class_score": 0.005825042724609375}, "domain": "pixel"}, {"position": {"minX": 416.5, "minY": 576.0, "maxX": 618.5, "maxY": 695.0}, "class_id": 1, "box_caption": "DRONE 0.006", "scores": {"class_score": 0.00582122802734375}, "domain": "pixel"}, {"position": {"minX": 79.75, "minY": 224.0, "maxX": 133.25, "maxY": 259.0}, "class_id": 1, "box_caption": "DRONE 0.006", "scores": {"class_score": 0.005817413330078125}, "domain": "pixel"}, {"position": {"minX": 411.0, "minY": 501.5, "maxX": 562.5, "maxY": 668.5}, "class_id": 0, "box_caption": "AIRPLANE 0.006", "scores": {"class_score": 0.005817413330078125}, "domain": "pixel"}, {"position": {"minX": -26.75, "minY": 433.5, "maxX": 383.75, "maxY": 877.5}, "class_id": 1, "box_caption": "DRONE 0.006", "scores": {"class_score": 0.005809783935546875}, "domain": "pixel"}, {"position": {"minX": -1.625, "minY": 277.25, "maxX": 155.875, "maxY": 308.25}, "class_id": 0, "box_caption": "AIRPLANE 0.006", "scores": {"class_score": 0.0057830810546875}, "domain": "pixel"}, {"position": {"minX": 69.5, "minY": 340.0, "maxX": 364.75, "maxY": 378.0}, "class_id": 1, "box_caption": "DRONE 0.006", "scores": {"class_score": 0.0057830810546875}, "domain": "pixel"}, {"position": {"minX": 14.5, "minY": 90.6875, "maxX": 177.75, "maxY": 287.0}, "class_id": 1, "box_caption": "DRONE 0.006", "scores": {"class_score": 0.005767822265625}, "domain": "pixel"}, {"position": {"minX": 116.9375, "minY": 467.75, "maxX": 280.75, "maxY": 572.5}, "class_id": 1, "box_caption": "DRONE 0.006", "scores": {"class_score": 0.0057525634765625}, "domain": "pixel"}, {"position": {"minX": 250.0, "minY": 235.0, "maxX": 888.0, "maxY": 797.0}, "class_id": 1, "box_caption": "DRONE 0.006", "scores": {"class_score": 0.0057525634765625}, "domain": "pixel"}, {"position": {"minX": 327.75, "minY": -51.875, "maxX": 450.75, "maxY": 178.0}, "class_id": 1, "box_caption": "DRONE 0.006", "scores": {"class_score": 0.005733489990234375}, "domain": "pixel"}, {"position": {"minX": 327.75, "minY": -83.1875, "maxX": 609.0, "maxY": 112.6875}, "class_id": 1, "box_caption": "DRONE 0.006", "scores": {"class_score": 0.005710601806640625}, "domain": "pixel"}, {"position": {"minX": 568.5, "minY": 294.0, "maxX": 715.5, "maxY": 377.5}, "class_id": 1, "box_caption": "DRONE 0.006", "scores": {"class_score": 0.005702972412109375}, "domain": "pixel"}, {"position": {"minX": 620.0, "minY": 391.5, "maxX": 640.0, "maxY": 537.0}, "class_id": 1, "box_caption": "DRONE 0.006", "scores": {"class_score": 0.00569915771484375}, "domain": "pixel"}], "class_labels": {"0": "AIRPLANE", "1": "DRONE"}}