{"box_data": [{"position": {"minX": 241.25, "minY": 74.625, "maxX": 598.0, "maxY": 398.5}, "class_id": 0, "box_caption": "person 0.965", "scores": {"class_score": 0.96484375}, "domain": "pixel"}, {"position": {"minX": 418.0, "minY": 279.0, "maxX": 598.0, "maxY": 401.0}, "class_id": 55, "box_caption": "cake 0.902", "scores": {"class_score": 0.90185546875}, "domain": "pixel"}, {"position": {"minX": 387.0, "minY": 246.5, "maxX": 485.0, "maxY": 401.0}, "class_id": 27, "box_caption": "tie 0.866", "scores": {"class_score": 0.86572265625}, "domain": "pixel"}, {"position": {"minX": 537.5, "minY": 147.125, "maxX": 556.5, "maxY": 172.125}, "class_id": 42, "box_caption": "fork 0.150", "scores": {"class_score": 0.1495361328125}, "domain": "pixel"}, {"position": {"minX": 498.25, "minY": 252.0, "maxX": 533.5, "maxY": 285.0}, "class_id": 41, "box_caption": "cup 0.084", "scores": {"class_score": 0.08441162109375}, "domain": "pixel"}, {"position": {"minX": 21.125, "minY": 44.375, "maxX": 368.5, "maxY": 402.5}, "class_id": 61, "box_caption": "toilet 0.041", "scores": {"class_score": 0.041412353515625}, "domain": "pixel"}, {"position": {"minX": 536.5, "minY": 147.75, "maxX": 563.5, "maxY": 209.0}, "class_id": 42, "box_caption": "fork 0.036", "scores": {"class_score": 0.03607177734375}, "domain": "pixel"}, {"position": {"minX": 537.0, "minY": 147.0, "maxX": 557.0, "maxY": 172.75}, "class_id": 40, "box_caption": "wine glass 0.009", "scores": {"class_score": 0.008819580078125}, "domain": "pixel"}, {"position": {"minX": 390.0, "minY": 246.0, "maxX": 483.0, "maxY": 307.5}, "class_id": 27, "box_caption": "tie 0.008", "scores": {"class_score": 0.008453369140625}, "domain": "pixel"}, {"position": {"minX": 534.0, "minY": 143.125, "maxX": 568.0, "maxY": 217.625}, "class_id": 40, "box_caption": "wine glass 0.008", "scores": {"class_score": 0.0083770751953125}, "domain": "pixel"}, {"position": {"minX": 418.0, "minY": 344.75, "maxX": 597.0, "maxY": 403.25}, "class_id": 55, "box_caption": "cake 0.008", "scores": {"class_score": 0.00782012939453125}, "domain": "pixel"}, {"position": {"minX": 537.5, "minY": 147.25, "maxX": 557.5, "maxY": 173.0}, "class_id": 44, "box_caption": "spoon 0.008", "scores": {"class_score": 0.007740020751953125}, "domain": "pixel"}, {"position": {"minX": 528.0, "minY": 146.75, "maxX": 567.0, "maxY": 217.5}, "class_id": 42, "box_caption": "fork 0.006", "scores": {"class_score": 0.0063934326171875}, "domain": "pixel"}, {"position": {"minX": 514.5, "minY": 146.25, "maxX": 595.5, "maxY": 353.5}, "class_id": 0, "box_caption": "person 0.006", "scores": {"class_score": 0.006130218505859375}, "domain": "pixel"}, {"position": {"minX": 30.0, "minY": 47.8125, "maxX": 365.5, "maxY": 268.5}, "class_id": 61, "box_caption": "toilet 0.005", "scores": {"class_score": 0.004756927490234375}, "domain": "pixel"}, {"position": {"minX": 384.0, "minY": 274.75, "maxX": 600.0, "maxY": 401.25}, "class_id": 60, "box_caption": "dining table 0.003", "scores": {"class_score": 0.00324249267578125}, "domain": "pixel"}, {"position": {"minX": 509.0, "minY": 147.25, "maxX": 568.0, "maxY": 253.75}, "class_id": 42, "box_caption": "fork 0.003", "scores": {"class_score": 0.0029277801513671875}, "domain": "pixel"}, {"position": {"minX": 496.75, "minY": 252.75, "maxX": 532.0, "maxY": 283.75}, "class_id": 43, "box_caption": "knife 0.003", "scores": {"class_score": 0.00289154052734375}, "domain": "pixel"}, {"position": {"minX": 537.5, "minY": 147.25, "maxX": 557.5, "maxY": 173.0}, "class_id": 43, "box_caption": "knife 0.003", "scores": {"class_score": 0.002593994140625}, "domain": "pixel"}, {"position": {"minX": 387.0, "minY": 246.5, "maxX": 485.0, "maxY": 401.0}, "class_id": 75, "box_caption": "vase 0.002", "scores": {"class_score": 0.0022792816162109375}, "domain": "pixel"}, {"position": {"minX": 254.0, "minY": 287.0, "maxX": 291.0, "maxY": 341.5}, "class_id": 65, "box_caption": "remote 0.002", "scores": {"class_score": 0.0022106170654296875}, "domain": "pixel"}, {"position": {"minX": 498.0, "minY": 253.25, "maxX": 533.0, "maxY": 284.25}, "class_id": 40, "box_caption": "wine glass 0.002", "scores": {"class_score": 0.0021266937255859375}, "domain": "pixel"}, {"position": {"minX": 535.0, "minY": 143.625, "maxX": 565.0, "maxY": 212.875}, "class_id": 44, "box_caption": "spoon 0.002", "scores": {"class_score": 0.00209808349609375}, "domain": "pixel"}, {"position": {"minX": 497.5, "minY": 251.5, "maxX": 534.5, "maxY": 288.0}, "class_id": 55, "box_caption": "cake 0.002", "scores": {"class_score": 0.0020694732666015625}, "domain": "pixel"}, {"position": {"minX": 532.5, "minY": 146.375, "maxX": 556.5, "maxY": 204.375}, "class_id": 42, "box_caption": "fork 0.002", "scores": {"class_score": 0.00199127197265625}, "domain": "pixel"}, {"position": {"minX": 385.0, "minY": 198.0, "maxX": 424.0, "maxY": 226.5}, "class_id": 55, "box_caption": "cake 0.002", "scores": {"class_score": 0.0018482208251953125}, "domain": "pixel"}, {"position": {"minX": 417.0, "minY": 279.75, "maxX": 578.5, "maxY": 354.25}, "class_id": 55, "box_caption": "cake 0.002", "scores": {"class_score": 0.0015172958374023438}, "domain": "pixel"}, {"position": {"minX": 495.5, "minY": 138.75, "maxX": 571.5, "maxY": 284.75}, "class_id": 42, "box_caption": "fork 0.001", "scores": {"class_score": 0.0014553070068359375}, "domain": "pixel"}, {"position": {"minX": 30.625, "minY": 47.8125, "maxX": 367.5, "maxY": 266.25}, "class_id": 71, "box_caption": "sink 0.001", "scores": {"class_score": 0.0012578964233398438}, "domain": "pixel"}, {"position": {"minX": 283.0, "minY": 338.0, "maxX": 297.0, "maxY": 359.0}, "class_id": 74, "box_caption": "clock 0.001", "scores": {"class_score": 0.0012531280517578125}, "domain": "pixel"}, {"position": {"minX": 486.25, "minY": 145.75, "maxX": 568.0, "maxY": 277.5}, "class_id": 41, "box_caption": "cup 0.001", "scores": {"class_score": 0.0012149810791015625}, "domain": "pixel"}, {"position": {"minX": 254.75, "minY": 283.5, "maxX": 292.25, "maxY": 344.0}, "class_id": 44, "box_caption": "spoon 0.001", "scores": {"class_score": 0.0012054443359375}, "domain": "pixel"}, {"position": {"minX": 285.5, "minY": 345.25, "maxX": 297.0, "maxY": 361.75}, "class_id": 74, "box_caption": "clock 0.001", "scores": {"class_score": 0.0012006759643554688}, "domain": "pixel"}, {"position": {"minX": 257.0, "minY": 288.75, "maxX": 291.0, "maxY": 341.25}, "class_id": 41, "box_caption": "cup 0.001", "scores": {"class_score": 0.0011806488037109375}, "domain": "pixel"}, {"position": {"minX": 536.0, "minY": 146.375, "maxX": 560.0, "maxY": 196.375}, "class_id": 44, "box_caption": "spoon 0.001", "scores": {"class_score": 0.00115966796875}, "domain": "pixel"}, {"position": {"minX": 384.25, "minY": 202.0, "maxX": 424.75, "maxY": 230.0}, "class_id": 45, "box_caption": "bowl 0.001", "scores": {"class_score": 0.001071929931640625}, "domain": "pixel"}, {"position": {"minX": 387.75, "minY": 247.875, "maxX": 483.75, "maxY": 398.5}, "class_id": 39, "box_caption": "bottle 0.001", "scores": {"class_score": 0.0010662078857421875}, "domain": "pixel"}, {"position": {"minX": 535.5, "minY": 145.75, "maxX": 562.5, "maxY": 213.75}, "class_id": 43, "box_caption": "knife 0.001", "scores": {"class_score": 0.0010595321655273438}, "domain": "pixel"}, {"position": {"minX": 19.875, "minY": 41.75, "maxX": 370.0, "maxY": 405.0}, "class_id": 60, "box_caption": "dining table 0.001", "scores": {"class_score": 0.0010538101196289062}, "domain": "pixel"}], "class_labels": {"0": "person", "1": "bicycle", "2": "car", "3": "motorcycle", "4": "airplane", "5": "bus", "6": "train", "7": "truck", "8": "boat", "9": "traffic light", "10": "fire hydrant", "11": "stop sign", "12": "parking meter", "13": "bench", "14": "bird", "15": "cat", "16": "dog", "17": "horse", "18": "sheep", "19": "cow", "20": "elephant", "21": "bear", "22": "zebra", "23": "giraffe", "24": "backpack", "25": "umbrella", "26": "handbag", "27": "tie", "28": "suitcase", "29": "frisbee", "30": "skis", "31": "snowboard", "32": "sports ball", "33": "kite", "34": "baseball bat", "35": "baseball glove", "36": "skateboard", "37": "surfboard", "38": "tennis racket", "39": "bottle", "40": "wine glass", "41": "cup", "42": "fork", "43": "knife", "44": "spoon", "45": "bowl", "46": "banana", "47": "apple", "48": "sandwich", "49": "orange", "50": "broccoli", "51": "carrot", "52": "hot dog", "53": "pizza", "54": "donut", "55": "cake", "56": "chair", "57": "couch", "58": "potted plant", "59": "bed", "60": "dining table", "61": "toilet", "62": "tv", "63": "laptop", "64": "mouse", "65": "remote", "66": "keyboard", "67": "cell phone", "68": "microwave", "69": "oven", "70": "toaster", "71": "sink", "72": "refrigerator", "73": "book", "74": "clock", "75": "vase", "76": "scissors", "77": "teddy bear", "78": "hair drier", "79": "toothbrush"}}